{
  "project_info": {
    "project_number": "295998494261",
    "firebase_url": "https://noturningback-c4045-default-rtdb.europe-west1.firebasedatabase.app",
    "project_id": "noturningback-c4045",
    "storage_bucket": "noturningback-c4045.firebasestorage.app"
  },
  "client": [
    {
      "client_info": {
        "mobilesdk_app_id": "1:295998494261:android:b046403b88127b9911c37c",
        "android_client_info": {
          "package_name": "com.example.noturningback"
        }
      },
      "oauth_client": [],
      "api_key": [
        {
          "current_key": "AIzaSyBk3TKPmOSp1gg6KjU7g4ZFon7VvFeruLw"
        }
      ],
      "services": {
        "appinvite_service": {
          "other_platform_oauth_client": []
        }
      }
    }
  ],
  "configuration_version": "1"
}